{
  "source": "lumen.types.AudioFormatType",
  "doc": "",
  "links": [],
  "toplinks": [],
  "sections": [
    {
      "name": "Values",
      "link": "#Values",
      "values": [
        {
          "name": "unknown",
          "signature": "lumen.types.AudioFormatType.unknown",
          "doc": ""
        },
        {
          "name": "ogg",
          "signature": "lumen.types.AudioFormatType.ogg",
          "doc": ""
        },
        {
          "name": "wav",
          "signature": "lumen.types.AudioFormatType.wav",
          "doc": ""
        },
        {
          "name": "pcm",
          "signature": "lumen.types.AudioFormatType.pcm",
          "doc": ""
        }
      ]
    },
    {
      "name": "Meta",
      "link": "#Meta",
      "values": [
        {
          "name": ":flatEnum",
          "value": ""
        }
      ]
    }
  ]
}